piso/__init__.py
piso/_decorators.py
piso/_exceptions.py
piso/accessor.py
piso/docstrings/accessor.py
piso/docstrings/interval.py
piso/docstrings/intervalarray.py
piso/docstrings/ndframe.py
piso/graph.py
piso/interval.py
piso/intervalarray.py
piso/ndframe.py
piso/util.py
piso-1.2.0.dist-info/LICENSE
piso-1.2.0.dist-info/METADATA
piso-1.2.0.dist-info/WHEEL
piso-1.2.0.dist-info/RECORD
