Metadata-Version: 2.1
Name: piso
Version: 1.2.0
Summary: Pandas Interval Set Operations: methods for set operations, analytics, lookups and joins on pandas' Interval, IntervalArray and IntervalIndex
Home-page: https://github.com/staircase-dev/piso
License: MIT
Keywords: piso,pandas,set,set operations,interval,IntervalArray,IntervalIndex,Data Analysis,Analysis,Data Structures
Author: Riley Clement
Author-email: venaturum@gmail.com
Maintainer: Riley Clement
Maintainer-email: venaturum@gmail.com
Requires-Python: >=3.9,<4.0
Classifier: Intended Audience :: Science/Research
Classifier: License :: OSI Approved :: MIT License
Classifier: Operating System :: OS Independent
Classifier: Programming Language :: Python :: 3
Classifier: Programming Language :: Python :: 3.9
Classifier: Programming Language :: Python :: 3.10
Classifier: Programming Language :: Python :: 3.11
Classifier: Programming Language :: Python :: 3.12
Classifier: Programming Language :: Python :: 3.13
Classifier: Topic :: Scientific/Engineering
Provides-Extra: codecov
Requires-Dist: numpy (>=1.17,<2.0) ; python_version >= "3.9" and python_version < "3.10"
Requires-Dist: numpy (>=1.21.2,<3) ; python_version >= "3.10" and python_version < "4.0"
Requires-Dist: pandas (>=1,<2) ; python_version >= "3.9" and python_version < "3.10"
Requires-Dist: pandas (>=1.3.4,<3) ; python_version >= "3.10" and python_version < "4.0"
Requires-Dist: staircase (>=2.1.0,<3.0.0)
Project-URL: Bug Tracker, https://github.com/staircase-dev/piso/issues
Project-URL: Documentation, https://piso.readthedocs.io
Project-URL: Repository, https://github.com/staircase-dev/piso
